{
  "last_node_id": 38,
  "last_link_id": 33,
  "nodes": [
    {
      "id": 8,
      "type": "VAEDecode",
      "pos": [
        1885.2000122070312,
        130
      ],
      "size": {
        "0": 210,
        "1": 46
      },
      "flags": {},
      "order": 13,
      "mode": 0,
      "inputs": [
        {
          "name": "samples",
          "type": "LATENT",
          "link": 20
        },
        {
          "name": "vae",
          "type": "VAE",
          "link": 4
        }
      ],
      "outputs": [
        {
          "name": "IMAGE",
          "type": "IMAGE",
          "links": [
            12
          ],
          "shape": 3
        }
      ],
      "properties": {
        "Node name for S&R": "VAEDecode"
      }
    },
    {
      "id": 28,
      "type": "ControlNetLoader",
      "pos": [
        -91,
        726
      ],
      "size": {
        "0": 400.5160217285156,
        "1": 64.84219360351562
      },
      "flags": {},
      "order": 0,
      "mode": 0,
      "outputs": [
        {
          "name": "CONTROL_NET",
          "type": "CONTROL_NET",
          "links": [
            15
          ],
          "shape": 3
        }
      ],
      "properties": {
        "Node name for S&R": "ControlNetLoader"
      },
      "widgets_values": [
        "diffusers_xl_canny_full.safetensors"
      ]
    },
    {
      "id": 14,
      "type": "KSamplerSelect",
      "pos": [
        1109,
        604
      ],
      "size": {
        "0": 315,
        "1": 58
      },
      "flags": {},
      "order": 1,
      "mode": 0,
      "outputs": [
        {
          "name": "SAMPLER",
          "type": "SAMPLER",
          "links": [
            8
          ],
          "shape": 3
        }
      ],
      "properties": {
        "Node name for S&R": "KSamplerSelect"
      },
      "widgets_values": [
        "dpmpp_2m"
      ]
    },
    {
      "id": 7,
      "type": "CLIPTextEncode",
      "pos": [
        613,
        693
      ],
      "size": {
        "0": 400,
        "1": 200
      },
      "flags": {},
      "order": 6,
      "mode": 0,
      "inputs": [
        {
          "name": "clip",
          "type": "CLIP",
          "link": 2
        }
      ],
      "outputs": [
        {
          "name": "CONDITIONING",
          "type": "CONDITIONING",
          "links": [
            14
          ],
          "shape": 3
        }
      ],
      "properties": {
        "Node name for S&R": "CLIPTextEncode"
      },
      "widgets_values": [
        "text, watermark, painting, worst quality, low quality,"
      ]
    },
    {
      "id": 25,
      "type": "PreviewImage",
      "pos": [
        2195.2000122070312,
        130
      ],
      "size": {
        "0": 1297.3590087890625,
        "1": 797.7919311523438
      },
      "flags": {},
      "order": 14,
      "mode": 0,
      "inputs": [
        {
          "name": "images",
          "type": "IMAGE",
          "link": 12
        }
      ],
      "properties": {
        "Node name for S&R": "PreviewImage"
      }
    },
    {
      "id": 22,
      "type": "SDTurboScheduler",
      "pos": [
        515,
        130
      ],
      "size": {
        "0": 315,
        "1": 82
      },
      "flags": {},
      "order": 4,
      "mode": 0,
      "inputs": [
        {
          "name": "model",
          "type": "MODEL",
          "link": 11
        }
      ],
      "outputs": [
        {
          "name": "SIGMAS",
          "type": "SIGMAS",
          "links": [
            9
          ],
          "shape": 3
        }
      ],
      "properties": {
        "Node name for S&R": "SDTurboScheduler"
      },
      "widgets_values": [
        10,
        1
      ]
    },
    {
      "id": 34,
      "type": "PreviewImage",
      "pos": [
        1546,
        637
      ],
      "size": [
        607.5040784627354,
        459.3012960475737
      ],
      "flags": {},
      "order": 9,
      "mode": 0,
      "inputs": [
        {
          "name": "images",
          "type": "IMAGE",
          "link": 29
        }
      ],
      "properties": {
        "Node name for S&R": "PreviewImage"
      }
    },
    {
      "id": 36,
      "type": "Canny",
      "pos": [
        651,
        1165
      ],
      "size": {
        "0": 315,
        "1": 82
      },
      "flags": {},
      "order": 7,
      "mode": 0,
      "inputs": [
        {
          "name": "image",
          "type": "IMAGE",
          "link": 28
        }
      ],
      "outputs": [
        {
          "name": "IMAGE",
          "type": "IMAGE",
          "links": [
            29,
            30
          ],
          "shape": 3,
          "slot_index": 0
        }
      ],
      "properties": {
        "Node name for S&R": "Canny"
      },
      "widgets_values": [
        0.01,
        0.5
      ]
    },
    {
      "id": 5,
      "type": "EmptyLatentImage",
      "pos": [
        120,
        94
      ],
      "size": [
        315,
        106
      ],
      "flags": {},
      "order": 11,
      "mode": 0,
      "inputs": [
        {
          "name": "width",
          "type": "INT",
          "link": 32,
          "widget": {
            "name": "width"
          }
        },
        {
          "name": "height",
          "type": "INT",
          "link": 33,
          "widget": {
            "name": "height"
          }
        }
      ],
      "outputs": [
        {
          "name": "LATENT",
          "type": "LATENT",
          "links": [
            10
          ],
          "shape": 3,
          "slot_index": 0
        }
      ],
      "properties": {
        "Node name for S&R": "EmptyLatentImage"
      },
      "widgets_values": [
        2104,
        1104,
        1
      ]
    },
    {
      "id": 29,
      "type": "ControlNetApplyAdvanced",
      "pos": [
        1004,
        69
      ],
      "size": {
        "0": 315,
        "1": 166
      },
      "flags": {},
      "order": 10,
      "mode": 0,
      "inputs": [
        {
          "name": "positive",
          "type": "CONDITIONING",
          "link": 13
        },
        {
          "name": "negative",
          "type": "CONDITIONING",
          "link": 14
        },
        {
          "name": "control_net",
          "type": "CONTROL_NET",
          "link": 15
        },
        {
          "name": "image",
          "type": "IMAGE",
          "link": 30
        }
      ],
      "outputs": [
        {
          "name": "positive",
          "type": "CONDITIONING",
          "links": [
            6
          ],
          "shape": 3
        },
        {
          "name": "negative",
          "type": "CONDITIONING",
          "links": [
            7
          ],
          "shape": 3
        }
      ],
      "properties": {
        "Node name for S&R": "ControlNetApplyAdvanced"
      },
      "widgets_values": [
        0.5,
        0,
        1
      ]
    },
    {
      "id": 13,
      "type": "SamplerCustom",
      "pos": [
        1451,
        254
      ],
      "size": {
        "0": 355.20001220703125,
        "1": 230
      },
      "flags": {},
      "order": 12,
      "mode": 0,
      "inputs": [
        {
          "name": "model",
          "type": "MODEL",
          "link": 5
        },
        {
          "name": "positive",
          "type": "CONDITIONING",
          "link": 6
        },
        {
          "name": "negative",
          "type": "CONDITIONING",
          "link": 7
        },
        {
          "name": "sampler",
          "type": "SAMPLER",
          "link": 8
        },
        {
          "name": "sigmas",
          "type": "SIGMAS",
          "link": 9
        },
        {
          "name": "latent_image",
          "type": "LATENT",
          "link": 10
        }
      ],
      "outputs": [
        {
          "name": "output",
          "type": "LATENT",
          "links": [
            20
          ],
          "shape": 3,
          "slot_index": 0
        },
        {
          "name": "denoised_output",
          "type": "LATENT",
          "links": [],
          "shape": 3,
          "slot_index": 1
        }
      ],
      "properties": {
        "Node name for S&R": "SamplerCustom"
      },
      "widgets_values": [
        true,
        202742126863306,
        "randomize",
        4
      ]
    },
    {
      "id": 20,
      "type": "CheckpointLoaderSimple",
      "pos": [
        -37,
        486
      ],
      "size": {
        "0": 433.4156188964844,
        "1": 102.89935302734375
      },
      "flags": {},
      "order": 2,
      "mode": 0,
      "outputs": [
        {
          "name": "MODEL",
          "type": "MODEL",
          "links": [
            5,
            11
          ],
          "shape": 3
        },
        {
          "name": "CLIP",
          "type": "CLIP",
          "links": [
            1,
            2
          ],
          "shape": 3
        },
        {
          "name": "VAE",
          "type": "VAE",
          "links": [
            4
          ],
          "shape": 3
        }
      ],
      "properties": {
        "Node name for S&R": "CheckpointLoaderSimple"
      },
      "widgets_values": [
        "dreamshaperXL_v21TurboDPMSDE.safetensors"
      ]
    },
    {
      "id": 37,
      "type": "GetImageSize+",
      "pos": [
        -273,
        324
      ],
      "size": {
        "0": 210,
        "1": 46
      },
      "flags": {},
      "order": 8,
      "mode": 0,
      "inputs": [
        {
          "name": "image",
          "type": "IMAGE",
          "link": 31
        }
      ],
      "outputs": [
        {
          "name": "width",
          "type": "INT",
          "links": [
            32
          ],
          "shape": 3,
          "slot_index": 0
        },
        {
          "name": "height",
          "type": "INT",
          "links": [
            33
          ],
          "shape": 3,
          "slot_index": 1
        }
      ],
      "properties": {
        "Node name for S&R": "GetImageSize+"
      }
    },
    {
      "id": 30,
      "type": "LoadImage",
      "pos": [
        -651,
        881
      ],
      "size": {
        "0": 315,
        "1": 314
      },
      "flags": {},
      "order": 3,
      "mode": 0,
      "outputs": [
        {
          "name": "IMAGE",
          "type": "IMAGE",
          "links": [
            28,
            31
          ],
          "shape": 3,
          "slot_index": 0
        },
        {
          "name": "MASK",
          "type": "MASK",
          "links": null,
          "shape": 3
        }
      ],
      "properties": {
        "Node name for S&R": "LoadImage"
      },
      "widgets_values": [
        "200 (5).png",
        "image"
      ]
    },
    {
      "id": 6,
      "type": "CLIPTextEncode",
      "pos": [
        612,
        364
      ],
      "size": {
        "0": 448.47955322265625,
        "1": 255.84902954101562
      },
      "flags": {},
      "order": 5,
      "mode": 0,
      "inputs": [
        {
          "name": "clip",
          "type": "CLIP",
          "link": 1
        }
      ],
      "outputs": [
        {
          "name": "CONDITIONING",
          "type": "CONDITIONING",
          "links": [
            13
          ],
          "shape": 3
        }
      ],
      "properties": {
        "Node name for S&R": "CLIPTextEncode"
      },
      "widgets_values": [
        "photo of residential buildings, each building with different scandinavian colour, taken from a street, people, cars, sunny day"
      ]
    }
  ],
  "links": [
    [
      1,
      20,
      1,
      6,
      0,
      "CLIP"
    ],
    [
      2,
      20,
      1,
      7,
      0,
      "CLIP"
    ],
    [
      4,
      20,
      2,
      8,
      1,
      "VAE"
    ],
    [
      5,
      20,
      0,
      13,
      0,
      "MODEL"
    ],
    [
      6,
      29,
      0,
      13,
      1,
      "CONDITIONING"
    ],
    [
      7,
      29,
      1,
      13,
      2,
      "CONDITIONING"
    ],
    [
      8,
      14,
      0,
      13,
      3,
      "SAMPLER"
    ],
    [
      9,
      22,
      0,
      13,
      4,
      "SIGMAS"
    ],
    [
      10,
      5,
      0,
      13,
      5,
      "LATENT"
    ],
    [
      11,
      20,
      0,
      22,
      0,
      "MODEL"
    ],
    [
      12,
      8,
      0,
      25,
      0,
      "IMAGE"
    ],
    [
      13,
      6,
      0,
      29,
      0,
      "CONDITIONING"
    ],
    [
      14,
      7,
      0,
      29,
      1,
      "CONDITIONING"
    ],
    [
      15,
      28,
      0,
      29,
      2,
      "CONTROL_NET"
    ],
    [
      20,
      13,
      0,
      8,
      0,
      "LATENT"
    ],
    [
      28,
      30,
      0,
      36,
      0,
      "IMAGE"
    ],
    [
      29,
      36,
      0,
      34,
      0,
      "IMAGE"
    ],
    [
      30,
      36,
      0,
      29,
      3,
      "IMAGE"
    ],
    [
      31,
      30,
      0,
      37,
      0,
      "IMAGE"
    ],
    [
      32,
      37,
      0,
      5,
      0,
      "INT"
    ],
    [
      33,
      37,
      1,
      5,
      1,
      "INT"
    ]
  ],
  "groups": [],
  "config": {},
  "extra": {},
  "version": 0.4
}